kg_vis/__init__.py
kg_vis/run.py
kg_vis/static/Associations_jiagu.csv
kg_vis/static/Associations_jiagu.json
kg_vis/static/FoodSafetyAriticles.xlsx
kg_vis/static/FoodSafetySentences_jiagu.xlsx
kg_vis/static/bootstrap.css
kg_vis/static/bootstrap.js
kg_vis/static/echarts.min.js
kg_vis/static/jquery-3.3.1.min.js
kg_vis/static/jquery.blockUI.js
kg_vis/static/jquery.form.min.js
kg_vis/templates/home.html
kg_vis-0.0.2.dist-info/LICENCE
kg_vis-0.0.2.dist-info/METADATA
kg_vis-0.0.2.dist-info/WHEEL
kg_vis-0.0.2.dist-info/top_level.txt
kg_vis-0.0.2.dist-info/RECORD
